unit-tests/verilog_generator/counter/compare_data/counter48.v
/* ============================================================
*
* Copyright (c) 2010 Computer Architecture Group, University of Heidelberg
*
* All rights reserved.
*
* University of Heidelberg
* Computer Architecture Group
* B6 26
* 68131 Mannheim
* Germany
* http://ra.ziti.uni-heidelberg.de/
*
* Author     :  Mondrian Nuessle
* Create Date:  07/07/10
* Design Name:  counter48
* Module Name:  counter48
* Description:  An loadable up-counter with a maximum width of 48 bit.
*                Supports DSP Slices on Xilinx.
*
* Facts for a 32 bit implementation, using the counter_eval.v as top-module, ISE11.3, constrained to 250 MHz on Virtex4-11
*
*  DSP Implementation:
*  68 IOB FFs
*  1 FF
*  1 LUT
*  1 Slice
*  1 DSP48
*  244 MHz
*
*  Fabric Implementation:
*   66 IOB FFs
*   65 FF
*   96 LUT
*   75 Slice
*   0 DSP48
*   216 MHz

*
* Revision:     Revision 1.0.0
*
* ===========================================================*/
//`timescale 1ns/10ps
//`include "technology.h"

module counter48 #(
		parameter DATASIZE	= 16,	// width of the counter, must be <=48 bits!
	    parameter LOADABLE	= 1		// whether the counter can be loaded at runtime
	) (
		input wire					clk,
	    input wire					res_n,
		input wire					increment,
		input wire	[DATASIZE-1:0]	load,
		input wire					load_enable,
		output wire [DATASIZE-1:0]	value
);

	reg [DATASIZE-1:0]	value_reg;
	reg [DATASIZE-1:0]	load_reg;
	reg					load_enable_reg;
//	reg					increment_reg;

	assign value	= value_reg;

	`ifdef ASYNC_RES
	always @(posedge clk or negedge res_n) `else
	always @(posedge clk) `endif
	begin
		if (!res_n)
		begin
			value_reg				<= {DATASIZE{1'b0}};
			load_enable_reg			<= 1'b0;
//			increment_reg			<= 1'b0;
			load_reg				<= {DATASIZE{1'b0}};
//			value_reg				<= {DATASIZE{1'b0}};
		end
		else
		begin
			load_reg				<= load;
			load_enable_reg			<= load_enable;
//			increment_reg			<= increment;
//			value					<=value_reg;
			case ({load_enable_reg,increment})
					2'b00:
						value_reg	<= value_reg;
					2'b01:
						value_reg	<= (value_reg + 1'b1);
					2'b10:
						value_reg	<= load_reg;
					2'b11:
						value_reg	<= load_reg + 1'b1; //arguable if we need to do this
			endcase
		end
	end

endmodule

unit-tests/verilog_generator/counter/compare_data/counter_RF.v


/* auto generated by RFG */
/* address map
tsc: 0x0

*/
/* instantiation template
counter_RF counter_RF_I (
	.res_n(),
	.clk(),
	.address(),
	.read_data(),
	.invalid_address(),
	.access_complete(),
	.read_en(),
	.write_en(),
	.write_data(),
	.tsc_cnt_next(),
	.tsc_cnt(),
	.tsc_cnt_wen(),
	.tsc_cnt_countup()
);
*/
module counter_RF
(
	///\defgroup sys
	///@{ 
	input wire res_n,
	input wire clk,
	///}@ 
	///\defgroup rw_if
	///@{ 
	input wire[3:3] address,
	output reg[63:0] read_data,
	output reg invalid_address,
	output reg access_complete,
	input wire read_en,
	input wire write_en,
	input wire[63:0] write_data,
	///}@ 
	input wire[47:0] tsc_cnt_next,
	output wire[47:0] tsc_cnt,
	input wire tsc_cnt_wen,
	input wire tsc_cnt_countup

);

	reg tsc_cnt_load_enable;
	reg[47:0] tsc_cnt_load_value;

	counter48 #(
		.DATASIZE(48)
	) tsc_I (
		.clk(clk),
		.res_n(res_n),
		.increment(tsc_cnt_countup),
		.load(tsc_cnt_load_value),
		.load_enable(tsc_cnt_load_enable),
		.value(tsc_cnt)
	);


	/* register tsc */
	`ifdef ASYNC_RES
	always @(posedge clk or negedge res_n) `else
	always @(posedge clk) `endif
	begin
		if (!res_n)
		begin
			tsc_cnt_load_enable <= 1'b0;
		end
		else
		begin

			if((address[3:3]== 0) && write_en)
			begin
				tsc_cnt_load_enable <= 1'b1;
				tsc_cnt_load_value <= write_data[47:0];
			end
			else if(tsc_cnt_wen)
			begin
				tsc_cnt_load_enable <= 1'b1;
				tsc_cnt_load_value <= tsc_cnt_next;
			end
			else
			begin
				tsc_cnt_load_enable <= 1'b0;
			end
		end
	end


	`ifdef ASYNC_RES
	always @(posedge clk or negedge res_n) `else
	always @(posedge clk) `endif
	begin
		if (!res_n)
		begin
			invalid_address <= 1'b0;
			access_complete <= 1'b0;
			`ifdef ASIC
			read_data   <= 64'b0;
			`endif
		end
		else
		begin

			casex(address[3:3])
				1'h0:
				begin
					read_data[47:0] <= tsc_cnt;
					read_data[63:48] <= 16'b0;
					invalid_address <= 1'b0;
					access_complete <= write_en || read_en;
				end
				default:
				begin
					invalid_address <= read_en || write_en;
					access_complete <= read_en || write_en;
				end		
			endcase
		end
	end
endmodule

unit-tests/verilog_generator/counter/compare_data/counter_RF_tb.v
// Author: Tobias Markus
module counter_RF_tb();

    parameter PERIOD =10;
    integer i;
    reg res_n;
    reg clk=0;
    reg address;
    wire[63:0] read_data;
    wire invalid_address;
    wire access_complete;
    reg read_en;
    reg write_en;
    reg[63:0] write_data;
    reg[47:0] tsc_cnt_next;
    wire[47:0] tsc_cnt;
    reg tsc_cnt_wen;
    reg tsc_cnt_countup;

    counter_RF counter_RF_I (
        .res_n(res_n),
        .clk(clk),
        .address(address),
        .read_data(read_data),
        .invalid_address(invalid_address),
        .access_complete(access_complete),
        .read_en(read_en),
        .write_en(write_en),
        .write_data(write_data),
        .tsc_cnt_next(tsc_cnt_next),
        .tsc_cnt(tsc_cnt),
        .tsc_cnt_wen(tsc_cnt_wen),
        .tsc_cnt_countup(tsc_cnt_countup));

    always
    begin
        #(PERIOD/2) clk <= ~clk;
    end

    initial
    begin
        $dumpfile("counter_RF.vcd");
        $dumpvars(0,counter_RF_tb);
        res_n <= 1'b0;
        read_en <= 1'b0;
        write_en <= 1'b0;
        tsc_cnt_wen <= 1'b0;
        address <= 1'b0;
        #10
        res_n <= 1'b1;
        tsc_cnt_countup <= 1'b1;
        for(i=0;i<200;i=i+1)
        begin
            @(negedge(clk));
            if (tsc_cnt != i) begin
                $error("tsc_cnt does not match counting value i...");
                $stop;
            end
        end
        tsc_cnt_countup <= 1'b0;
        tsc_cnt_wen <= 1'b1;
        tsc_cnt_next <= 400;
        @(negedge(clk));
        @(negedge(clk));
        tsc_cnt_countup <= 1'b1;
        tsc_cnt_wen <= 1'b0;
        @(negedge(clk));
        for(i=401;i<600;i=i+1)
        begin
            @(negedge(clk));
            if (tsc_cnt != i) 
            begin
                $error("tsc_cnt does not macht conting value after load");
                $stop;
            end
        end
        $stop;
    end

endmodule

unit-tests/verilog_generator/counter/counter_RF.vcd
$date
	Wed Mar  5 13:42:05 2014
$end
$version
	Icarus Verilog
$end
$timescale
	1s
$end
$scope module counter_RF_tb $end
$var wire 1 ! access_complete $end
$var wire 1 " invalid_address $end
$var wire 64 # read_data [63:0] $end
$var wire 48 $ tsc_cnt [47:0] $end
$var reg 1 % address $end
$var reg 1 & clk $end
$var integer 32 ' i [31:0] $end
$var reg 1 ( read_en $end
$var reg 1 ) res_n $end
$var reg 1 * tsc_cnt_countup $end
$var reg 48 + tsc_cnt_next [47:0] $end
$var reg 1 , tsc_cnt_wen $end
$var reg 64 - write_data [63:0] $end
$var reg 1 . write_en $end
$scope module counter_RF_I $end
$var wire 1 / address [3:3] $end
$var wire 1 0 clk $end
$var wire 1 1 read_en $end
$var wire 1 2 res_n $end
$var wire 48 3 tsc_cnt [47:0] $end
$var wire 1 4 tsc_cnt_countup $end
$var wire 48 5 tsc_cnt_next [47:0] $end
$var wire 1 6 tsc_cnt_wen $end
$var wire 64 7 write_data [63:0] $end
$var wire 1 8 write_en $end
$var reg 1 9 access_complete $end
$var reg 1 : invalid_address $end
$var reg 64 ; read_data [63:0] $end
$var reg 1 < tsc_cnt_load_enable $end
$var reg 48 = tsc_cnt_load_value [47:0] $end
$scope module tsc_I $end
$var wire 1 0 clk $end
$var wire 1 4 increment $end
$var wire 48 > load [47:0] $end
$var wire 1 ? load_enable $end
$var wire 1 2 res_n $end
$var wire 48 @ value [47:0] $end
$var reg 1 A load_enable_reg $end
$var reg 48 B load_reg [47:0] $end
$var reg 48 C value_reg [47:0] $end
$upscope $end
$upscope $end
$upscope $end
$enddefinitions $end
#0
$dumpvars
bx C
bx B
xA
bx @
x?
bx >
bx =
x<
bx ;
x:
x9
08
bx 7
06
bx 5
x4
bx 3
02
01
00
0/
0.
bx -
0,
bx +
x*
0)
0(
bx '
0&
0%
bx $
bx #
x"
x!
$end
#5
b0 B
0A
b0 C
b0 $
b0 3
b0 @
0<
0?
09
0!
0:
0"
1&
10
#10
0&
00
1*
14
1)
12
b1 '
#15
b0 ;
b0 #
b1 C
b1 $
b1 3
b1 @
bx B
1&
10
#20
b10 '
0&
00
#25
b10 C
b10 $
b10 3
b10 @
b1 ;
b1 #
1&
10
#30
b11 '
0&
00
#35
b10 ;
b10 #
b11 C
b11 $
b11 3
b11 @
1&
10
#40
b100 '
0&
00
#45
b100 C
b100 $
b100 3
b100 @
b11 ;
b11 #
1&
10
#50
b101 '
0&
00
#55
b100 ;
b100 #
b101 C
b101 $
b101 3
b101 @
1&
10
#60
b110 '
0&
00
#65
b110 C
b110 $
b110 3
b110 @
b101 ;
b101 #
1&
10
#70
b111 '
0&
00
#75
b110 ;
b110 #
b111 C
b111 $
b111 3
b111 @
1&
10
#80
b1000 '
0&
00
#85
b1000 C
b1000 $
b1000 3
b1000 @
b111 ;
b111 #
1&
10
#90
b1001 '
0&
00
#95
b1000 ;
b1000 #
b1001 C
b1001 $
b1001 3
b1001 @
1&
10
#100
b1010 '
0&
00
#105
b1010 C
b1010 $
b1010 3
b1010 @
b1001 ;
b1001 #
1&
10
#110
b1011 '
0&
00
#115
b1010 ;
b1010 #
b1011 C
b1011 $
b1011 3
b1011 @
1&
10
#120
b1100 '
0&
00
#125
b1100 C
b1100 $
b1100 3
b1100 @
b1011 ;
b1011 #
1&
10
#130
b1101 '
0&
00
#135
b1100 ;
b1100 #
b1101 C
b1101 $
b1101 3
b1101 @
1&
10
#140
b1110 '
0&
00
#145
b1110 C
b1110 $
b1110 3
b1110 @
b1101 ;
b1101 #
1&
10
#150
b1111 '
0&
00
#155
b1110 ;
b1110 #
b1111 C
b1111 $
b1111 3
b1111 @
1&
10
#160
b10000 '
0&
00
#165
b10000 C
b10000 $
b10000 3
b10000 @
b1111 ;
b1111 #
1&
10
#170
b10001 '
0&
00
#175
b10000 ;
b10000 #
b10001 C
b10001 $
b10001 3
b10001 @
1&
10
#180
b10010 '
0&
00
#185
b10010 C
b10010 $
b10010 3
b10010 @
b10001 ;
b10001 #
1&
10
#190
b10011 '
0&
00
#195
b10010 ;
b10010 #
b10011 C
b10011 $
b10011 3
b10011 @
1&
10
#200
b10100 '
0&
00
#205
b10100 C
b10100 $
b10100 3
b10100 @
b10011 ;
b10011 #
1&
10
#210
b10101 '
0&
00
#215
b10100 ;
b10100 #
b10101 C
b10101 $
b10101 3
b10101 @
1&
10
#220
b10110 '
0&
00
#225
b10110 C
b10110 $
b10110 3
b10110 @
b10101 ;
b10101 #
1&
10
#230
b10111 '
0&
00
#235
b10110 ;
b10110 #
b10111 C
b10111 $
b10111 3
b10111 @
1&
10
#240
b11000 '
0&
00
#245
b11000 C
b11000 $
b11000 3
b11000 @
b10111 ;
b10111 #
1&
10
#250
b11001 '
0&
00
#255
b11000 ;
b11000 #
b11001 C
b11001 $
b11001 3
b11001 @
1&
10
#260
b11010 '
0&
00
#265
b11010 C
b11010 $
b11010 3
b11010 @
b11001 ;
b11001 #
1&
10
#270
b11011 '
0&
00
#275
b11010 ;
b11010 #
b11011 C
b11011 $
b11011 3
b11011 @
1&
10
#280
b11100 '
0&
00
#285
b11100 C
b11100 $
b11100 3
b11100 @
b11011 ;
b11011 #
1&
10
#290
b11101 '
0&
00
#295
b11100 ;
b11100 #
b11101 C
b11101 $
b11101 3
b11101 @
1&
10
#300
b11110 '
0&
00
#305
b11110 C
b11110 $
b11110 3
b11110 @
b11101 ;
b11101 #
1&
10
#310
b11111 '
0&
00
#315
b11110 ;
b11110 #
b11111 C
b11111 $
b11111 3
b11111 @
1&
10
#320
b100000 '
0&
00
#325
b100000 C
b100000 $
b100000 3
b100000 @
b11111 ;
b11111 #
1&
10
#330
b100001 '
0&
00
#335
b100000 ;
b100000 #
b100001 C
b100001 $
b100001 3
b100001 @
1&
10
#340
b100010 '
0&
00
#345
b100010 C
b100010 $
b100010 3
b100010 @
b100001 ;
b100001 #
1&
10
#350
b100011 '
0&
00
#355
b100010 ;
b100010 #
b100011 C
b100011 $
b100011 3
b100011 @
1&
10
#360
b100100 '
0&
00
#365
b100100 C
b100100 $
b100100 3
b100100 @
b100011 ;
b100011 #
1&
10
#370
b100101 '
0&
00
#375
b100100 ;
b100100 #
b100101 C
b100101 $
b100101 3
b100101 @
1&
10
#380
b100110 '
0&
00
#385
b100110 C
b100110 $
b100110 3
b100110 @
b100101 ;
b100101 #
1&
10
#390
b100111 '
0&
00
#395
b100110 ;
b100110 #
b100111 C
b100111 $
b100111 3
b100111 @
1&
10
#400
b101000 '
0&
00
#405
b101000 C
b101000 $
b101000 3
b101000 @
b100111 ;
b100111 #
1&
10
#410
b101001 '
0&
00
#415
b101000 ;
b101000 #
b101001 C
b101001 $
b101001 3
b101001 @
1&
10
#420
b101010 '
0&
00
#425
b101010 C
b101010 $
b101010 3
b101010 @
b101001 ;
b101001 #
1&
10
#430
b101011 '
0&
00
#435
b101010 ;
b101010 #
b101011 C
b101011 $
b101011 3
b101011 @
1&
10
#440
b101100 '
0&
00
#445
b101100 C
b101100 $
b101100 3
b101100 @
b101011 ;
b101011 #
1&
10
#450
b101101 '
0&
00
#455
b101100 ;
b101100 #
b101101 C
b101101 $
b101101 3
b101101 @
1&
10
#460
b101110 '
0&
00
#465
b101110 C
b101110 $
b101110 3
b101110 @
b101101 ;
b101101 #
1&
10
#470
b101111 '
0&
00
#475
b101110 ;
b101110 #
b101111 C
b101111 $
b101111 3
b101111 @
1&
10
#480
b110000 '
0&
00
#485
b110000 C
b110000 $
b110000 3
b110000 @
b101111 ;
b101111 #
1&
10
#490
b110001 '
0&
00
#495
b110000 ;
b110000 #
b110001 C
b110001 $
b110001 3
b110001 @
1&
10
#500
b110010 '
0&
00
#505
b110010 C
b110010 $
b110010 3
b110010 @
b110001 ;
b110001 #
1&
10
#510
b110011 '
0&
00
#515
b110010 ;
b110010 #
b110011 C
b110011 $
b110011 3
b110011 @
1&
10
#520
b110100 '
0&
00
#525
b110100 C
b110100 $
b110100 3
b110100 @
b110011 ;
b110011 #
1&
10
#530
b110101 '
0&
00
#535
b110100 ;
b110100 #
b110101 C
b110101 $
b110101 3
b110101 @
1&
10
#540
b110110 '
0&
00
#545
b110110 C
b110110 $
b110110 3
b110110 @
b110101 ;
b110101 #
1&
10
#550
b110111 '
0&
00
#555
b110110 ;
b110110 #
b110111 C
b110111 $
b110111 3
b110111 @
1&
10
#560
b111000 '
0&
00
#565
b111000 C
b111000 $
b111000 3
b111000 @
b110111 ;
b110111 #
1&
10
#570
b111001 '
0&
00
#575
b111000 ;
b111000 #
b111001 C
b111001 $
b111001 3
b111001 @
1&
10
#580
b111010 '
0&
00
#585
b111010 C
b111010 $
b111010 3
b111010 @
b111001 ;
b111001 #
1&
10
#590
b111011 '
0&
00
#595
b111010 ;
b111010 #
b111011 C
b111011 $
b111011 3
b111011 @
1&
10
#600
b111100 '
0&
00
#605
b111100 C
b111100 $
b111100 3
b111100 @
b111011 ;
b111011 #
1&
10
#610
b111101 '
0&
00
#615
b111100 ;
b111100 #
b111101 C
b111101 $
b111101 3
b111101 @
1&
10
#620
b111110 '
0&
00
#625
b111110 C
b111110 $
b111110 3
b111110 @
b111101 ;
b111101 #
1&
10
#630
b111111 '
0&
00
#635
b111110 ;
b111110 #
b111111 C
b111111 $
b111111 3
b111111 @
1&
10
#640
b1000000 '
0&
00
#645
b1000000 C
b1000000 $
b1000000 3
b1000000 @
b111111 ;
b111111 #
1&
10
#650
b1000001 '
0&
00
#655
b1000000 ;
b1000000 #
b1000001 C
b1000001 $
b1000001 3
b1000001 @
1&
10
#660
b1000010 '
0&
00
#665
b1000010 C
b1000010 $
b1000010 3
b1000010 @
b1000001 ;
b1000001 #
1&
10
#670
b1000011 '
0&
00
#675
b1000010 ;
b1000010 #
b1000011 C
b1000011 $
b1000011 3
b1000011 @
1&
10
#680
b1000100 '
0&
00
#685
b1000100 C
b1000100 $
b1000100 3
b1000100 @
b1000011 ;
b1000011 #
1&
10
#690
b1000101 '
0&
00
#695
b1000100 ;
b1000100 #
b1000101 C
b1000101 $
b1000101 3
b1000101 @
1&
10
#700
b1000110 '
0&
00
#705
b1000110 C
b1000110 $
b1000110 3
b1000110 @
b1000101 ;
b1000101 #
1&
10
#710
b1000111 '
0&
00
#715
b1000110 ;
b1000110 #
b1000111 C
b1000111 $
b1000111 3
b1000111 @
1&
10
#720
b1001000 '
0&
00
#725
b1001000 C
b1001000 $
b1001000 3
b1001000 @
b1000111 ;
b1000111 #
1&
10
#730
b1001001 '
0&
00
#735
b1001000 ;
b1001000 #
b1001001 C
b1001001 $
b1001001 3
b1001001 @
1&
10
#740
b1001010 '
0&
00
#745
b1001010 C
b1001010 $
b1001010 3
b1001010 @
b1001001 ;
b1001001 #
1&
10
#750
b1001011 '
0&
00
#755
b1001010 ;
b1001010 #
b1001011 C
b1001011 $
b1001011 3
b1001011 @
1&
10
#760
b1001100 '
0&
00
#765
b1001100 C
b1001100 $
b1001100 3
b1001100 @
b1001011 ;
b1001011 #
1&
10
#770
b1001101 '
0&
00
#775
b1001100 ;
b1001100 #
b1001101 C
b1001101 $
b1001101 3
b1001101 @
1&
10
#780
b1001110 '
0&
00
#785
b1001110 C
b1001110 $
b1001110 3
b1001110 @
b1001101 ;
b1001101 #
1&
10
#790
b1001111 '
0&
00
#795
b1001110 ;
b1001110 #
b1001111 C
b1001111 $
b1001111 3
b1001111 @
1&
10
#800
b1010000 '
0&
00
#805
b1010000 C
b1010000 $
b1010000 3
b1010000 @
b1001111 ;
b1001111 #
1&
10
#810
b1010001 '
0&
00
#815
b1010000 ;
b1010000 #
b1010001 C
b1010001 $
b1010001 3
b1010001 @
1&
10
#820
b1010010 '
0&
00
#825
b1010010 C
b1010010 $
b1010010 3
b1010010 @
b1010001 ;
b1010001 #
1&
10
#830
b1010011 '
0&
00
#835
b1010010 ;
b1010010 #
b1010011 C
b1010011 $
b1010011 3
b1010011 @
1&
10
#840
b1010100 '
0&
00
#845
b1010100 C
b1010100 $
b1010100 3
b1010100 @
b1010011 ;
b1010011 #
1&
10
#850
b1010101 '
0&
00
#855
b1010100 ;
b1010100 #
b1010101 C
b1010101 $
b1010101 3
b1010101 @
1&
10
#860
b1010110 '
0&
00
#865
b1010110 C
b1010110 $
b1010110 3
b1010110 @
b1010101 ;
b1010101 #
1&
10
#870
b1010111 '
0&
00
#875
b1010110 ;
b1010110 #
b1010111 C
b1010111 $
b1010111 3
b1010111 @
1&
10
#880
b1011000 '
0&
00
#885
b1011000 C
b1011000 $
b1011000 3
b1011000 @
b1010111 ;
b1010111 #
1&
10
#890
b1011001 '
0&
00
#895
b1011000 ;
b1011000 #
b1011001 C
b1011001 $
b1011001 3
b1011001 @
1&
10
#900
b1011010 '
0&
00
#905
b1011010 C
b1011010 $
b1011010 3
b1011010 @
b1011001 ;
b1011001 #
1&
10
#910
b1011011 '
0&
00
#915
b1011010 ;
b1011010 #
b1011011 C
b1011011 $
b1011011 3
b1011011 @
1&
10
#920
b1011100 '
0&
00
#925
b1011100 C
b1011100 $
b1011100 3
b1011100 @
b1011011 ;
b1011011 #
1&
10
#930
b1011101 '
0&
00
#935
b1011100 ;
b1011100 #
b1011101 C
b1011101 $
b1011101 3
b1011101 @
1&
10
#940
b1011110 '
0&
00
#945
b1011110 C
b1011110 $
b1011110 3
b1011110 @
b1011101 ;
b1011101 #
1&
10
#950
b1011111 '
0&
00
#955
b1011110 ;
b1011110 #
b1011111 C
b1011111 $
b1011111 3
b1011111 @
1&
10
#960
b1100000 '
0&
00
#965
b1100000 C
b1100000 $
b1100000 3
b1100000 @
b1011111 ;
b1011111 #
1&
10
#970
b1100001 '
0&
00
#975
b1100000 ;
b1100000 #
b1100001 C
b1100001 $
b1100001 3
b1100001 @
1&
10
#980
b1100010 '
0&
00
#985
b1100010 C
b1100010 $
b1100010 3
b1100010 @
b1100001 ;
b1100001 #
1&
10
#990
b1100011 '
0&
00
#995
b1100010 ;
b1100010 #
b1100011 C
b1100011 $
b1100011 3
b1100011 @
1&
10
#1000
b1100100 '
0&
00
#1005
b1100100 C
b1100100 $
b1100100 3
b1100100 @
b1100011 ;
b1100011 #
1&
10
#1010
b1100101 '
0&
00
#1015
b1100100 ;
b1100100 #
b1100101 C
b1100101 $
b1100101 3
b1100101 @
1&
10
#1020
b1100110 '
0&
00
#1025
b1100110 C
b1100110 $
b1100110 3
b1100110 @
b1100101 ;
b1100101 #
1&
10
#1030
b1100111 '
0&
00
#1035
b1100110 ;
b1100110 #
b1100111 C
b1100111 $
b1100111 3
b1100111 @
1&
10
#1040
b1101000 '
0&
00
#1045
b1101000 C
b1101000 $
b1101000 3
b1101000 @
b1100111 ;
b1100111 #
1&
10
#1050
b1101001 '
0&
00
#1055
b1101000 ;
b1101000 #
b1101001 C
b1101001 $
b1101001 3
b1101001 @
1&
10
#1060
b1101010 '
0&
00
#1065
b1101010 C
b1101010 $
b1101010 3
b1101010 @
b1101001 ;
b1101001 #
1&
10
#1070
b1101011 '
0&
00
#1075
b1101010 ;
b1101010 #
b1101011 C
b1101011 $
b1101011 3
b1101011 @
1&
10
#1080
b1101100 '
0&
00
#1085
b1101100 C
b1101100 $
b1101100 3
b1101100 @
b1101011 ;
b1101011 #
1&
10
#1090
b1101101 '
0&
00
#1095
b1101100 ;
b1101100 #
b1101101 C
b1101101 $
b1101101 3
b1101101 @
1&
10
#1100
b1101110 '
0&
00
#1105
b1101110 C
b1101110 $
b1101110 3
b1101110 @
b1101101 ;
b1101101 #
1&
10
#1110
b1101111 '
0&
00
#1115
b1101110 ;
b1101110 #
b1101111 C
b1101111 $
b1101111 3
b1101111 @
1&
10
#1120
b1110000 '
0&
00
#1125
b1110000 C
b1110000 $
b1110000 3
b1110000 @
b1101111 ;
b1101111 #
1&
10
#1130
b1110001 '
0&
00
#1135
b1110000 ;
b1110000 #
b1110001 C
b1110001 $
b1110001 3
b1110001 @
1&
10
#1140
b1110010 '
0&
00
#1145
b1110010 C
b1110010 $
b1110010 3
b1110010 @
b1110001 ;
b1110001 #
1&
10
#1150
b1110011 '
0&
00
#1155
b1110010 ;
b1110010 #
b1110011 C
b1110011 $
b1110011 3
b1110011 @
1&
10
#1160
b1110100 '
0&
00
#1165
b1110100 C
b1110100 $
b1110100 3
b1110100 @
b1110011 ;
b1110011 #
1&
10
#1170
b1110101 '
0&
00
#1175
b1110100 ;
b1110100 #
b1110101 C
b1110101 $
b1110101 3
b1110101 @
1&
10
#1180
b1110110 '
0&
00
#1185
b1110110 C
b1110110 $
b1110110 3
b1110110 @
b1110101 ;
b1110101 #
1&
10
#1190
b1110111 '
0&
00
#1195
b1110110 ;
b1110110 #
b1110111 C
b1110111 $
b1110111 3
b1110111 @
1&
10
#1200
b1111000 '
0&
00
#1205
b1111000 C
b1111000 $
b1111000 3
b1111000 @
b1110111 ;
b1110111 #
1&
10
#1210
b1111001 '
0&
00
#1215
b1111000 ;
b1111000 #
b1111001 C
b1111001 $
b1111001 3
b1111001 @
1&
10
#1220
b1111010 '
0&
00
#1225
b1111010 C
b1111010 $
b1111010 3
b1111010 @
b1111001 ;
b1111001 #
1&
10
#1230
b1111011 '
0&
00
#1235
b1111010 ;
b1111010 #
b1111011 C
b1111011 $
b1111011 3
b1111011 @
1&
10
#1240
b1111100 '
0&
00
#1245
b1111100 C
b1111100 $
b1111100 3
b1111100 @
b1111011 ;
b1111011 #
1&
10
#1250
b1111101 '
0&
00
#1255
b1111100 ;
b1111100 #
b1111101 C
b1111101 $
b1111101 3
b1111101 @
1&
10
#1260
b1111110 '
0&
00
#1265
b1111110 C
b1111110 $
b1111110 3
b1111110 @
b1111101 ;
b1111101 #
1&
10
#1270
b1111111 '
0&
00
#1275
b1111110 ;
b1111110 #
b1111111 C
b1111111 $
b1111111 3
b1111111 @
1&
10
#1280
b10000000 '
0&
00
#1285
b10000000 C
b10000000 $
b10000000 3
b10000000 @
b1111111 ;
b1111111 #
1&
10
#1290
b10000001 '
0&
00
#1295
b10000000 ;
b10000000 #
b10000001 C
b10000001 $
b10000001 3
b10000001 @
1&
10
#1300
b10000010 '
0&
00
#1305
b10000010 C
b10000010 $
b10000010 3
b10000010 @
b10000001 ;
b10000001 #
1&
10
#1310
b10000011 '
0&
00
#1315
b10000010 ;
b10000010 #
b10000011 C
b10000011 $
b10000011 3
b10000011 @
1&
10
#1320
b10000100 '
0&
00
#1325
b10000100 C
b10000100 $
b10000100 3
b10000100 @
b10000011 ;
b10000011 #
1&
10
#1330
b10000101 '
0&
00
#1335
b10000100 ;
b10000100 #
b10000101 C
b10000101 $
b10000101 3
b10000101 @
1&
10
#1340
b10000110 '
0&
00
#1345
b10000110 C
b10000110 $
b10000110 3
b10000110 @
b10000101 ;
b10000101 #
1&
10
#1350
b10000111 '
0&
00
#1355
b10000110 ;
b10000110 #
b10000111 C
b10000111 $
b10000111 3
b10000111 @
1&
10
#1360
b10001000 '
0&
00
#1365
b10001000 C
b10001000 $
b10001000 3
b10001000 @
b10000111 ;
b10000111 #
1&
10
#1370
b10001001 '
0&
00
#1375
b10001000 ;
b10001000 #
b10001001 C
b10001001 $
b10001001 3
b10001001 @
1&
10
#1380
b10001010 '
0&
00
#1385
b10001010 C
b10001010 $
b10001010 3
b10001010 @
b10001001 ;
b10001001 #
1&
10
#1390
b10001011 '
0&
00
#1395
b10001010 ;
b10001010 #
b10001011 C
b10001011 $
b10001011 3
b10001011 @
1&
10
#1400
b10001100 '
0&
00
#1405
b10001100 C
b10001100 $
b10001100 3
b10001100 @
b10001011 ;
b10001011 #
1&
10
#1410
b10001101 '
0&
00
#1415
b10001100 ;
b10001100 #
b10001101 C
b10001101 $
b10001101 3
b10001101 @
1&
10
#1420
b10001110 '
0&
00
#1425
b10001110 C
b10001110 $
b10001110 3
b10001110 @
b10001101 ;
b10001101 #
1&
10
#1430
b10001111 '
0&
00
#1435
b10001110 ;
b10001110 #
b10001111 C
b10001111 $
b10001111 3
b10001111 @
1&
10
#1440
b10010000 '
0&
00
#1445
b10010000 C
b10010000 $
b10010000 3
b10010000 @
b10001111 ;
b10001111 #
1&
10
#1450
b10010001 '
0&
00
#1455
b10010000 ;
b10010000 #
b10010001 C
b10010001 $
b10010001 3
b10010001 @
1&
10
#1460
b10010010 '
0&
00
#1465
b10010010 C
b10010010 $
b10010010 3
b10010010 @
b10010001 ;
b10010001 #
1&
10
#1470
b10010011 '
0&
00
#1475
b10010010 ;
b10010010 #
b10010011 C
b10010011 $
b10010011 3
b10010011 @
1&
10
#1480
b10010100 '
0&
00
#1485
b10010100 C
b10010100 $
b10010100 3
b10010100 @
b10010011 ;
b10010011 #
1&
10
#1490
b10010101 '
0&
00
#1495
b10010100 ;
b10010100 #
b10010101 C
b10010101 $
b10010101 3
b10010101 @
1&
10
#1500
b10010110 '
0&
00
#1505
b10010110 C
b10010110 $
b10010110 3
b10010110 @
b10010101 ;
b10010101 #
1&
10
#1510
b10010111 '
0&
00
#1515
b10010110 ;
b10010110 #
b10010111 C
b10010111 $
b10010111 3
b10010111 @
1&
10
#1520
b10011000 '
0&
00
#1525
b10011000 C
b10011000 $
b10011000 3
b10011000 @
b10010111 ;
b10010111 #
1&
10
#1530
b10011001 '
0&
00
#1535
b10011000 ;
b10011000 #
b10011001 C
b10011001 $
b10011001 3
b10011001 @
1&
10
#1540
b10011010 '
0&
00
#1545
b10011010 C
b10011010 $
b10011010 3
b10011010 @
b10011001 ;
b10011001 #
1&
10
#1550
b10011011 '
0&
00
#1555
b10011010 ;
b10011010 #
b10011011 C
b10011011 $
b10011011 3
b10011011 @
1&
10
#1560
b10011100 '
0&
00
#1565
b10011100 C
b10011100 $
b10011100 3
b10011100 @
b10011011 ;
b10011011 #
1&
10
#1570
b10011101 '
0&
00
#1575
b10011100 ;
b10011100 #
b10011101 C
b10011101 $
b10011101 3
b10011101 @
1&
10
#1580
b10011110 '
0&
00
#1585
b10011110 C
b10011110 $
b10011110 3
b10011110 @
b10011101 ;
b10011101 #
1&
10
#1590
b10011111 '
0&
00
#1595
b10011110 ;
b10011110 #
b10011111 C
b10011111 $
b10011111 3
b10011111 @
1&
10
#1600
b10100000 '
0&
00
#1605
b10100000 C
b10100000 $
b10100000 3
b10100000 @
b10011111 ;
b10011111 #
1&
10
#1610
b10100001 '
0&
00
#1615
b10100000 ;
b10100000 #
b10100001 C
b10100001 $
b10100001 3
b10100001 @
1&
10
#1620
b10100010 '
0&
00
#1625
b10100010 C
b10100010 $
b10100010 3
b10100010 @
b10100001 ;
b10100001 #
1&
10
#1630
b10100011 '
0&
00
#1635
b10100010 ;
b10100010 #
b10100011 C
b10100011 $
b10100011 3
b10100011 @
1&
10
#1640
b10100100 '
0&
00
#1645
b10100100 C
b10100100 $
b10100100 3
b10100100 @
b10100011 ;
b10100011 #
1&
10
#1650
b10100101 '
0&
00
#1655
b10100100 ;
b10100100 #
b10100101 C
b10100101 $
b10100101 3
b10100101 @
1&
10
#1660
b10100110 '
0&
00
#1665
b10100110 C
b10100110 $
b10100110 3
b10100110 @
b10100101 ;
b10100101 #
1&
10
#1670
b10100111 '
0&
00
#1675
b10100110 ;
b10100110 #
b10100111 C
b10100111 $
b10100111 3
b10100111 @
1&
10
#1680
b10101000 '
0&
00
#1685
b10101000 C
b10101000 $
b10101000 3
b10101000 @
b10100111 ;
b10100111 #
1&
10
#1690
b10101001 '
0&
00
